{"cameraMode":{"drawMode":0,"name":"Shaded","section":"Shading Mode"},"sceneLighting":true,"audioPlay":false,"sceneViewState":{"showFog":true,"showMaterialUpdate":false,"showSkybox":true,"showFlares":true,"showImageEffects":true,"showParticleSystems":true},"in2DMode":false,"pivot":{"x":-75.85386657714844,"y":-27.9329833984375,"z":115.3758316040039},"rotation":{"x":0.13297449052333833,"y":-0.7136162519454956,"z":0.14094340801239015,"w":0.6732401251792908},"size":48.4561882019043,"orthographic":false}